Workbook
Name _ftn1: 'All-in-1-sheet'!#REF!
Name _ftn1: 'BET-S(5)LCE'!#REF!
Name _ftn2: 'All-in-1-sheet'!#REF!
Name _ftn2: 'BET-S(5)LCE'!#REF!
Name _ftn3: 'All-in-1-sheet'!#REF!
Name _ftn3: 'BET-S(5)LCE'!#REF!
Name _ftnref1: 'All-in-1-sheet'!$A$93
Name _ftnref1: 'BET-S(5)LCE'!$A$94
Name _ftnref2: 'All-in-1-sheet'!$A$72
Name _ftnref2: 'BET-S(5)LCE'!$A$73
Name _ftnref3: 'All-in-1-sheet'!#REF!
Name _ftnref3: 'BET-S(5)LCE'!#REF!

Sheet All-in-1-sheet
A1: input
A4: BET-S (Hub Only) | E4: BET-C (Depot Slow & Hub Fast) | I4: Diesel Trucks (Depot&Hub)
A6: Assumptions | E6: Assumptions | I6: Assumptions
A7: 1. A truck discussed in this model is a heavy-duty vehicle consists of a 6×2 tractor unit. 2. BET fuel economy is assumed to have 0.5% decreasing for BET-S because of better management and maintenance. 3. All future cash flows and amortised costs are assumed to pay at the end of each year when accounting for discounted values. | E7: 1. A truck discussed in this model is a heavy-duty vehicle consists of a 6×2 tractor unit. 2. BET fuel economy is assumed to increase every year at 1.4%. 3. All future cash flows and amortised costs are assumed to pay at the end of each year when accounting for discounted values. | I7: 1. A truck discussed in this model is a heavy duty vehicle consists of a 6×2 tractor unit. 2. The fuel economy is assumed to increase every year at 1.1%. 3. All future cash flows and amortised costs are assumed to pay at the end of each year when accounting for discounted values.
A8: Parameter | B8: Units | C8: Public Available Value | E8: Parameter | F8: Units | G8: Public Available Value | I8: Parameter | J8: Units | K8: Public Available Value
A9: Truck specifications | E9: Truck specifications | I9: Truck specifications
A10: Electric Glider Price | B10: £ | C10: 130000 | E10: Electric Glider Price | F10: £ | G10: =C10 -> 130000
A11: Battery modules per truck | B11: modules/truck | C11: 3 | E11: Total battery capacity | F11: kWh | G11: 513 | I11: Diesel truck CAPEX | J11: £ | K11: 144900
A12: Glider Fixed depreciation rate | B12: - | C12: 0.075 | E12: Initial battery price | F12: £/kWh | G12: =C29 -> 148 | I12: Fixed depreciation rate | J12: - | K12: =C12 -> 0.075
A13: Variable glider dipreciation per km | B13: £ | C13: 0.095 | E13: Electric truck CAPEX | F13: £ | G13: =G10+G11*G12 -> 205924 | I13: Variable depreciation per km | J13: £ | K13: =C13 -> 0.095
A14: Glider residual percentage | B14: - | C14: 0.2 | E14: Glider Fixed depreciation rate | F14: - | G14: =C12 -> 0.075 | I14: Truck lifetime | J14: years | K14: =C15 -> 15
A15: Glider lifetime | B15: years | C15: 15 | E15: Variable glider dipreciation per km | F15: £ | G15: =C13 -> 0.095 | I15: Cost of Capital | J15: - | K15: =C16 -> 0.125
A16: Cost of Capital | B16: - | C16: 0.125 | E16: Glider residual value percentage | F16: - | G16: =C14 -> 0.2 | I16: Upfront payment percentage | J16: - | K16: =C17 -> 0.3
A17: Upfront payment percentage | B17: - | C17: 0.3 | E17: Glider lifetime | F17: years | G17: =C15 -> 15 | I17: Loan Term | J17: years | K17: =C18 -> 5
A18: Loan Term | B18: years | C18: 5 | E18: Cost of Capital | F18: - | G18: =C16 -> 0.125 | I18: Loan Amount | J18: £ | K18: =K11*(1-K16) -> 101430
A19: Loan Amount | B19: £ | C19: =C10*(1-C17) -> 91000 | E19: Upfront payment percentage | F19: - | G19: =C17 -> 0.3 | I19: Upfront payment | J19: £ | K19: =K11*K16 -> 43470
A20: Upfront payment | B20: £ | C20: =C10*C17 -> 39000 | E20: Loan Term | F20: years | G20: =C18 -> 5 | I20: Interest payment per year | J20: £ | K20: =K11*(1-K16)*K15 -> 12678.75
A21: Interest payment per year | B21: £ | C21: =C10*(1-C17)*C16 -> 11375 | E21: Loan Amount | F21: £ | G21: =G13*(1-G19) -> 144146.8 | I21: Annual payment | J21: £ | K21: =-PMT(12.5%,5,K18) -> 28487.025
A22: Annual payment | B22: £ | C22: =-PMT(12.5%,5,C19) -> 25557.718 | E22: Upfront payment | F22: £ | G22: =G13*G19 -> 61777.2 | I22: Truck Total Costs NPV | J22: £ | K22: =K21*SUM(K98:K102)+K19 -> 151458.24
A23: Glider Total Costs NPV | B23: £ | C23: =C22*SUM(C98:C102)+C20 -> 135883.86 | E23: Interest payment per year | F23: £ | G23: =G13*(1-G19)*G18 -> 18018.35
E24: Annual payment | F24: £ | G24: =-PMT(12.5%,5,G21) -> 40484.211
E25: Truck Total Costs NPV | F25: £ | G25: =G24*SUM(G98:G102)+G22 -> 215244.21
A27: Battery specifications | E27: Battery specifications
A28: Battery pack capacity | B28: kWh | C28: 171 | E28: Battery residual percentage | F28: - | G28: =C30 -> 0.1
A29: Initial battery price | B29: £/kWh | C29: 148 | E29: Battery Lifetime cycle | F29: - | G29: =C31 -> 2200
A30: Battery residual percentage | B30: - | C30: 0.1 | E30: Battery lifetime | F30: years | G30: =G29/G44 -> 7.5342466
A31: Battery lifetime cycle | B31: cycles | C31: 2200
A32: Battery lifetime | B32: years | C32: =C31/C44 -> 7.5342466
A34: Truck Fixed Annual Operation Costs | E34: Truck Fixed Annual Operation Costs | I34: Truck Fixed Annual Operation Costs
A35: Annual service cost | B35: £/year | C35: 4200 | E35: Annual service cost | F35: £/year | G35: =C35 -> 4200 | I35: Annual service cost | J35: £/year | K35: 4800
A36: Diesel truck consistant Insurance | B36: £ | C36: ='Diesel(5)LCE'!C27 -> 10000 | E36: Diesel truck consistant Insurance | F36: £ | G36: =C36 -> 10000 | I36: Consistent Insurance | J36: £ | K36: 10000
A37: Insurance percentage on top of diesel truck | B37: - | C37: 0.2 | E37: Insurance percentage on top of diesel truck | F37: - | G37: =C37 -> 0.2 | I37: Driver costs per truck | J37: £ | K37: =K161*K45 -> 41469.84
A38: BET insurance | B38: £ | C38: =C36*(1+C37) -> 12000 | E38: BET insurance | F38: £ | G38: =G36*(1+G37) -> 12000
A39: Driver costs per truck | B39: £/year | C39: =C186*C45 -> 41469.84 | E39: Driver costs per truck | F39: £/year | G39: =G161*G45 -> 41469.84
A41: Truck Operarion Details | E41: Truck Operations Details | I41: Truck operations
A42: Daily distance driven with cargo per shift | B42: km | C42: 240 | E42: Daily distance driven with cargo per shift | F42: km | G42: =C42 -> 240 | I42: Daily distance driven with cargo per shift | J42: km | K42: =C42 -> 240
A43: Daily unladen distance driven per shift | B43: km | C43: =C42/7*3 -> 102.85714 | E43: Daily unladen distance driven per shift | F43: km | G43: =G42/7*3 -> 102.85714 | I43: Daily unladen distance driven per shift | J43: km | K43: =K42/7*3 -> 102.85714
A44: Operational days per year | B44: days | C44: 292 | E44: Operational days per year | F44: days | G44: =C44 -> 292 | I44: Operational days per year | J44: days | K44: =C44 -> 292
A45: Shift per day | B45: - | C45: 1 | E45: Shift per day | F45: - | G45: =C45 -> 1 | I45: Shift per day | J45: - | K45: =C45 -> 1
A46: Swaps per day | B46: swaps/day | C46: =MAX(1,(ROUNDUP(((C42+C43)*C45)/(C28*C11/C50),0))) -> 1 | E46: Charges per day | F46: Charges/day | G46: =MAX(1,(ROUNDUP(((G42+G43)*G45)/(G11/G50),0))) -> 1
A47: Truck fuel economy annual increase rate | B47: - | C47: 0.005 | E47: Truck fuel economy increase rate | F47: - | G47: 0.014 | I47: Truck fuel economy annual increase rate | J47: - | K47: 0.011
A48: Energy save when unladen | B48: - | C48: 0.25 | E48: Energy save compared to when full-loaded | F48: - | G48: =C48 -> 0.25 | I48: Energy save compared to when full-loaded | J48: - | K48: =C48 -> 0.25
A49: Offpeak swapping percentage | B49: - | C49: 0.5 | E49: Depot slow charging percentage | F49: - | G49: 0.8 | I49: Depot refuelling percentage | J49: - | K49: 0.8
A50: Battery energy intensity - Full Loaded | B50: kWh/km | C50: 1.37 | E50: Truck fuel economy in the first year -Full Loaded | F50: kWh/km | G50: =C50 -> 1.37 | I50: Daily diesel use in the first year | J50: l | K50: =K42*K$45*K55+K43*K$45*K60 -> 111
A51: Battery energy intensity - Full Loaded - Second Year | B51: kWh/km | C51: =C50*(1+C47) -> 1.37685 | E51: Truck fuel economy in the second year -Full Loaded | F51: kWh/km | G51: =G50*(1+G47) -> 1.38918 | I51: Daily diesel use in the second year | J51: l | K51: =K$42*K$45*K56+K$43*K$45*K61 -> 112.221
A52: Battery energy intensity - Full Loaded - Third Year | B52: kWh/km | C52: =C51*(1+C47) -> 1.3837342 | E52: Truck fuel economy in the third year -Full Loaded | F52: kWh/km | G52: =G51*(1+G47) -> 1.4086285 | I52: Daily diesel use in the third year | J52: l | K52: =K$42*K$45*K57+K$43*K$45*K62 -> 113.45543
A53: Battery energy intensity - Full Loaded - Fourth Year | B53: kWh/km | C53: =C52*(1+C47) -> 1.3906529 | E53: Truck fuel economy in the fourth year -Full Loaded | F53: kWh/km | G53: =G52*(1+G47) -> 1.4283493 | I53: Daily diesel use in the fourth year | J53: l | K53: =K$42*K$45*K58+K$43*K$45*K63 -> 114.70344
A54: Battery energy intensity - Full Loaded - Fifth Year | B54: kWh/km | C54: =C53*(1+C47) -> 1.3976062 | E54: Truck fuel economy in the fifth year -Full Loaded | F54: kWh/km | G54: =G53*(1+G47) -> 1.4483462 | I54: Daily diesel use in the fifth year | J54: l | K54: =K$42*K$45*K59+K$43*K$45*K64 -> 115.96518
A55: Battery energy intensity - Unladen | B55: KWh/km | C55: =C50*(1-C48) -> 1.0275 | E55: Truck fuel economy in the first year -Unladen | F55: kWh/km | G55: =G50*(1-G48) -> 1.0275 | I55: Truck fuel economy in the first year -Full Loaded | J55: l/km | K55: 0.35
A56: Battery energy intensity - Unladen - Second Year | B56: KWh/km | C56: =C51*(1-C48) -> 1.0326375 | E56: Truck fuel economy in the second year -Unladen | F56: kWh/km | G56: =G51*(1-G48) -> 1.041885 | I56: Truck fuel economy in the second year -Full Loaded | J56: l/km | K56: =K55*(1+K$47) -> 0.35385
A57: Battery energy intensity - Unladen - Third Year | B57: KWh/km | C57: =C52*(1-C48) -> 1.0378007 | E57: Truck fuel economy in the third year -Unladen | F57: kWh/km | G57: =G52*(1-G48) -> 1.0564714 | I57: Truck fuel economy in the third year -Full Loaded | J57: l/km | K57: =K56*(1+K$47) -> 0.35774235
A58: Battery energy intensity - Unladen - Fourth Year | B58: KWh/km | C58: =C53*(1-C48) -> 1.0429897 | E58: Truck fuel economy in the fourth year -Unladen | F58: kWh/km | G58: =G53*(1-G48) -> 1.071262 | I58: Truck fuel economy in the fourth year -Full Loaded | J58: l/km | K58: =K57*(1+K$47) -> 0.36167752
A59: Battery energy intensity - Unladen - Fifth Year | B59: KWh/km | C59: =C54*(1-C48) -> 1.0482046 | E59: Truck fuel economy in the fifth year -Unladen | F59: kWh/km | G59: =G54*(1-G48) -> 1.0862597 | I59: Truck fuel economy in the fifth year -Full Loaded | J59: l/km | K59: =K58*(1+K$47) -> 0.36565597
A60: Daily truck energy use | B60: kWh | C60: =(C$42*C$45*C50+C$43*C$45*C55) -> 434.48571 | E60: Daily truck energy use in the first year | F60: kWh | G60: =(G$42*G$45*G50+G$43*G$45*G55) -> 434.48571 | I60: Truck fuel economy in the first year -Unladen | J60: l/km | K60: =K55*(1-K48) -> 0.2625
A61: Daily truck energy use -Second Year | B61: kWh | C61: =(C$42*C$45*C51+C$43*C$45*C56) -> 436.65814 | E61: Daily truck energy use in the second year | F61: kWh | G61: =(G$42*G$45*G51+G$43*G$45*G56) -> 440.56851 | I61: Truck fuel economy in the second year -Unladen | J61: l/km | K61: =K56*(1-K48) -> 0.2653875
A62: Daily truck energy use -Third Year | B62: kWh | C62: =(C$42*C$45*C52+C$43*C$45*C57) -> 438.84143 | E62: Daily truck energy use in the third year | F62: kWh | G62: =(G$42*G$45*G52+G$43*G$45*G57) -> 446.73647 | I62: Truck fuel economy in the third year -Unladen | J62: l/km | K62: =K57*(1-K48) -> 0.26830676
A63: Daily truck energy use - Fourth Year | B63: kWh | C63: =(C$42*C$45*C53+C$43*C$45*C58) -> 441.03564 | E63: Daily truck energy use in the fourth year | F63: kWh | G63: =(G$42*G$45*G53+G$43*G$45*G58) -> 452.99078 | I63: Truck fuel economy in the fourth year -Unladen | J63: l/km | K63: =K58*(1-K48) -> 0.27125814
A64: Daily truck energy use -Fifth Year | B64: kWh | C64: =(C$42*C$45*C54+C$43*C$45*C59) -> 443.24082 | E64: Daily truck energy use in the fifth year | F64: kWh | G64: =(G$42*G$45*G54+G$43*G$45*G59) -> 459.33266 | I64: Truck fuel economy in the fifth year -Unladen | J64: l/km | K64: =K59*(1-K48) -> 0.27424198
I65: LEZ operation percentage | J65: - | K65: 0.1
A66: Station specifications | E66: Depot charging specifications | I66: LEZ operation Charge | J66: £ | K66: 50
A67: Battery CAPEX | B67: £ | C67: =C28*C29*(C71+C75*C11) -> 4479516 | E67: Charger CAPEX | F67: £/kWh | G67: 0.12
A68: Station CAPEX | B68: £ | C68: 2000000 | E68: Charger lifetime | F68: years | G68: 8 | I68: On-depot specifications
A69: Site CAPEX | B69: £ | C69: 1000000 | E69: Site CAPEX | F69: £/kWh | G69: 0.08 | I69: Bunker CAPEX | J69: £/l | K69: 0.24
E70: Site lifetime | F70: years | G70: 24 | I70: Bunker lifetime | J70: years | K70: 24
A71: Batteries in station | B71: # | C71: 24
A72: Station lifetime | B72: years | C72: 15 | E72: Charging operations | I72: Refuelling operations
A73: Max station service capacity | B73: trucks/day | C73: 171 | E73: On-depot retail energy price | F73: £/kWh | G73: 0.22 | I73: wholesale diesel price | J73: £/l | K73: 1.05
A74: Expected station utilisation | B74: - | C74: 0.3 | E74: Public hub electricity price | F74: £/kWh | G74: 0.39 | I74: Public hub diesel price | J74: £/l | K74: 1.48
A75: Expected station service demand | B75: trucks/day | C75: =ROUND(C73*C74,0) -> 51 | E75: Expected fleet size | F75: trucks | G75: 51 | I75: Expected fleet size | J75: trucks | K75: 51
A76: Station Costs and Revenue sources | E76: Annual energy requirement in the first year | F76: kWh/year | G76: =G60*G$75*G$44 -> 6470361.3 | I76: Expected diesel requirement in the first year | J76: l/day | K76: =K50*K75*K44 -> 1653012
A77: Station annual staff costs | B77: £/year | C77: 216000 | E77: Annual energy requirement in the second year | F77: kWh/year | G77: =G61*G$75*G$44 -> 6560946.3 | I77: Expected diesel requirement in the second year | J77: l/day | K77: =K51*K75*K44 -> 1671195.1
A78: Station annual cost on all other services | B78: £/year | C78: 48705 | E78: Annual energy requirement in the third year | F78: kWh/year | G78: =G62*G$75*G$44 -> 6652799.6 | I78: Expected diesel requirement in the third year | J78: l/day | K78: =K52*K75*K44 -> 1689578.3
A79: Annual Allocated Station Operating Cost per truck | B79: £ | C79: =(C77+C78)/C75 -> 5190.2941 | E79: Annual energy requirement in the fourth year | F79: kWh/year | G79: =G63*G$75*G$44 -> 6745938.8 | I79: Expected diesel requirement in the fourth year | J79: l/day | K79: =K53*K75*K44 -> 1708163.6
A80: Annual Allocated infrastructure depreciation per truck | B80: £ | C80: =((C68 + C69) / C72) / C75 -> 3921.5686 | E80: Annual energy requirement in the fifth year | F80: kWh/year | G80: =G64*G$75*G$44 -> 6840381.9 | I80: Expected diesel requirement in the fifth year | J80: l/day | K80: =K54*K75*K44 -> 1726953.4
A81: Annual Allocated battery depreciation per truck | B81: £ | C81: =(((C71*C28*C29)+(C75*C11*C28*C29))*(1-C30)*(C44*C45*C75*C11/((C71+(C75*C11))*C31)))/C75 -> 9069.4669 | E81: Annual on-depot demand in the first year | F81: kWh/year | G81: =G49*G76 -> 5176289 | I81: Annual on-depot demand in the first year | J81: l/day | K81: =K49*K76 -> 1322409.6
A82: Basic annual rent to cover BaaS costs | B82: £ | C82: =C81+C80+C79 -> 18181.33 | E82: Annual on-depot demand in the second year | F82: kWh/year | G82: =G49*G77 -> 5248757.1 | I82: Annual on-depot demand in the secodn year | J82: l/day | K82: =K49*K77 -> 1336956.1
A83: Basic monthly rent to cover costs | B83: £ | C83: =C82/12 -> 1515.1108 | E83: Annual on-depot demand in the third year | F83: kWh/year | G83: =G49*G78 -> 5322239.7 | I83: Annual on-depot demand in the third year | J83: l/day | K83: =K49*K78 -> 1351662.6
A84: Expected annual return on battery renting | B84: - | C84: 0.15 | E84: Annual on-depot demand in the fourth year | F84: kWh/year | G84: =G49*G79 -> 5396751 | I84: Annual on-depot demand in the fourth year | J84: l/day | K84: =K49*K79 -> 1366530.9
A85: Annual extra rent serves as profit | B85: £ | C85: =C29*C11*C28*C84 -> 11388.6 | E85: Annual on-depot demand in the fifth year | F85: kWh/year | G85: =G49*G80 -> 5472305.5 | I85: Annual on-depot demand in the fifth year | J85: l/day | K85: =K49*K80 -> 1381562.8
A86: Extra monthly rent | B86: £ | C86: =C85/12 -> 949.05 | E86: Annual public hub demand in the first year | F86: kWh/year | G86: =G76*(1-G49) -> 1294072.3 | I86: Annual public hub demand in the first year | J86: l/day | K86: =K76*(1-K49) -> 330602.4
A87: Swapping fee (flat rate) | B87: £ | C87: 3 | E87: Annual public hub demand in the second year | F87: kWh/year | G87: =G77*(1-G49) -> 1312189.3 | I87: Annual public hub demand in the second year | J87: l/day | K87: =K77*(1-K49) -> 334239.03
A88: Annual Swapping fee | B88: £ | C88: =C87*C46*C44 -> 876 | E88: Annual public hub demand in the third year | F88: kWh/year | G88: =G78*(1-G49) -> 1330559.9 | I88: Annual public hub demand in the third year | J88: l/day | K88: =K78*(1-K49) -> 337915.66
A89: Peak retail energy price-BaaS provider pays | B89: £/kWh | C89: 0.2 | E89: Annual public hub demand in the fourth year | F89: kWh/year | G89: =G79*(1-G49) -> 1349187.8 | I89: Annual public hub demand in the fourth year | J89: l/day | K89: =K79*(1-K49) -> 341632.73
A90: Off-peak retail energy price-BaaS provider pays | B90: £/kWh | C90: 0.1 | E90: Annual public hub demand in the fifth year | F90: kWh/year | G90: =G80*(1-G49) -> 1368076.4 | I90: Annual public hub demand in the fifth year | J90: l/day | K90: =K80*(1-K49) -> 345390.69
A91: Target electricity margin | B91: - | C91: 1
A92: Peak retail energy price-Fleet manager pays | B92: £/kWh | C92: =C89*(1+C91) -> 0.4
A93: Off-peak retail energy price-Fleet manager pays | B93: £/kWh | C93: =C90*(1+C91) -> 0.2
A95: Discounted Factors | E95: Discounted Factors | I95: Discounted Factors
A96: Discounted Rate | B96: - | C96: 0.1 | E96: Discounted Rate | F96: - | G96: =C96 -> 0.1 | I96: Discounted Rate | J96: - | K96: =C96 -> 0.1
A97: Discounted Factor: | E97: Discounted Factor: | I97: Discounted Factor:
A98: Year 1 | B98: - | C98: =1/(1+C96)^1 -> 0.90909091 | E98: Year 1 | F98: - | G98: =1/(1+G96)^1 -> 0.90909091 | I98: Year 1 | J98: - | K98: =1/(1+K96)^1 -> 0.90909091
A99: Year 2 | B99: - | C99: =1/(1+C96)^2 -> 0.82644628 | E99: Year 2 | F99: - | G99: =1/(1+G96)^2 -> 0.82644628 | I99: Year 2 | J99: - | K99: =1/(1+K96)^2 -> 0.82644628
A100: Year 3 | B100: - | C100: =1/(1+C96)^3 -> 0.7513148 | E100: Year 3 | F100: - | G100: =1/(1+G96)^3 -> 0.7513148 | I100: Year 3 | J100: - | K100: =1/(1+K96)^3 -> 0.7513148
A101: Year 4 | B101: - | C101: =1/(1+C96)^4 -> 0.68301346 | E101: Year 4 | F101: - | G101: =1/(1+G96)^4 -> 0.68301346 | I101: Year 4 | J101: - | K101: =1/(1+K96)^4 -> 0.68301346
A102: Year 5 | B102: - | C102: =1/(1+C96)^5 -> 0.62092132 | E102: Year 5 | F102: - | G102: =1/(1+G96)^5 -> 0.62092132 | I102: Year 5 | J102: - | K102: =1/(1+K96)^5 -> 0.62092132
A103: Subsidy | E103: Subsidy
A104: Subsidy | B104: £ | C104: 0 | E104: Subsidy | F104: £ | G104: 0
A106: Calculations | E106: Calculations | I106: Calculations | J106: Unit
A107: Time duration considered in TCO | B107: years | C107: 5 | E107: Time duration considered in TCO | F107: years | G107: =C107 -> 5 | I107: Time duration considered of TCO | J107: years | K107: =C107 -> 5
A108: Glider total cost NPV | B108: £ | C108: =C23 -> 135883.86 | E108: Truck acquisition cost NPV | F108: £ | G108: =G25 -> 215244.21 | I108: Truck acquisition cost NPV | J108: £ | K108: =K22 -> 151458.24
...

Sheet BET-S(5)LCE
A1: BET-S (Hub Only)
A3: Assumptions
A4: 1. A truck discussed in this model is a heavy-duty vehicle consists of a 6×2 tractor unit. 2. BET fuel economy is assumed to have 0.5% decreasing for BET-S because of better management and maintenance. 3. All future cash flows and amortised costs are assumed to pay at the end of each year when accounting for discounted values.
A5: Parameter | B5: Units | C5: Public Available Value | D5: Source | E5: Notes from Aegis | F5: Notes for public available data
A6: Truck specifications
A7: Electric Glider Price | B7: £ | C7: 130000 | D7: from Iveco
A8: Battery modules per truck | B8: modules/truck | C8: 3 | D8: (Qijiswap, 2025) (NewsQQ, 2024)
A9: Glider Fixed depreciation rate | B9: - | C9: 0.075 | D9: ICCT & …
A10: Variable glider dipreciation per km | B10: £ | C10: 0.095 | F10: Calibrated
A11: Glider residual percentage | B11: - | C11: 0.2 | D11: Aegis management assumption | E11: to align with Octopus numbers | F11: to align with Octopus numbers
A12: Glider lifetime | B12: years | C12: 15 | D12: Aegis management assumption | E12: based on "million mile" warranty claims in market 1 mile = c1.6 km => 15 years | F12: based on "million mile" warranty claims in market 1 mile = c1.6 km => 15 years
A13: Cost of Capital | B13: - | C13: 0.125
A14: Upfront payment percentage | B14: - | C14: 0.3
A15: Loan Term | B15: years | C15: 5
A16: Loan Amount | B16: £ | C16: =C7*(1-C14) -> 91000
A17: Upfront payment | B17: £ | C17: =C7*C14 -> 39000
A18: Interest payment per year | B18: £ | C18: =C7*(1-C14)*C13 -> 11375
A19: Annual payment | B19: £ | C19: =-PMT(C13,5,C16) -> 25557.718
A20: Glider Total Costs NPV | B20: £ | C20: =C19*SUM(C103:C107)+C17 -> 135883.86
A21: Electric glider acquisition cost - changes by 2030 | C21: 0.06
A22: Electric glider acquisition cost - changes by 2040 | C22: 0.03
A23: Glider weight | B23: kg | C23: 9986
A24: Glider Production Emission Factor | B24: kg CO2e/kg | C24: 7
A25: Glider Recycle Emission Saving | B25: - | C25: 0.17
A27: Battery specifications
A28: Battery pack capacity | B28: kWh | C28: 171 | D28: (Qijiswap, 2025) (NewsQQ, 2024)
A29: Initial battery price | B29: £/kWh | C29: 148 | D29: CATL provided quote | E29: Used in Aegis model - adjusted for exchange rate of CNY/GBP of 9.65 (CNY 1,430) | F29: Used in Aegis model - adjusted for exchange rate of CNY/GBP of 9.65 (CNY 1,430)
A30: Battery residual percentage | B30: - | C30: 0.1 | D30: Provided by Brunp | F30: Collected from Brunp consultation
A31: Battery lifetime cycle | B31: cycles | C31: 2200 | D31: ICCT,2021;ICCT,2021EU; ICCT2024 | F31: 2000/1500/3000
A32: Battery lifetime | B32: years | C32: =C31/C48 -> 7.5342466
A33: Battery Production Emission Factor | B33: kg CO2e/kWh | C33: 57
A34: Battery Recycle Emission Saving | B34: - | C34: 0.19
A35: Battery Second Life Capacity | B35: kWh | C35: =C28*0.8 -> 136.8
A36: Battery Sets Needed | B36: - | C36: 2
A38: Truck Fixed Annual Operation Costs
A39: Annual service cost | B39: £/year | C39: 4200 | D39: Same as BET-C
A40: Diesel truck consistant Insurance | B40: £ | C40: ='Diesel(5)LCE'!C27 -> 10000 | D40: (The electric car scheme, 2026) | F40: Electric car insurance through traditional channels costs 15-25% more than petrol equivalents in 2026.
A41: Insurance percentage on top of diesel truck | B41: - | C41: 0.2
A42: BET insurance | B42: £ | C42: =C40*(1+C41) -> 12000
A43: Driver costs per truck | B43: £/year | C43: =C205*C49 -> 41469.84
A45: Truck Operarion Details
A46: Daily distance driven with cargo per shift | B46: km | C46: 240 | E46: derived in model, but used as starting basis here | F46: Annual mileage is asumed to be 100,000km. Devided by 292 days. | G46: 100000
A47: Daily unladen distance driven per shift | B47: km | C47: =C46/7*3 -> 102.85714 | D47: (DfT, 2024) | F47: The ratio of full-loaded and unladen driven distance is 7:3 in the UK | G47: =G46/292 -> 342.46575
A48: Operational days per year | B48: days | C48: 292 | D48: Aegis management assumption | E48: 80% utilisation rate of trucks on days in the year basis | F48: 80% utilisation rate of trucks on days in the year basis | G48: =G47*0.7 -> 239.72603
A49: Shift per day | B49: - | C49: 1 | G49: =G47*0.3 -> 102.73973
A50: Swaps per day | B50: swaps/day | C50: =MAX(1,(ROUNDUP(((C46+C47)*C49)/(C28*C8/C54),0))) -> 1 | D50: Aegis management assumption
A51: Truck fuel economy annual increase rate | B51: - | C51: 0.005
A52: Energy save when unladen | B52: - | C52: 0.25 | D52: ICCT, 2022 | F52: Unladen trucks are assumed to have this % of energy saved compared to when full-loaded.
A53: Offpeak swapping percentage | B53: - | C53: 0.5 | D53: Aegis management assumption | E53: 7 hour window between 11pm and 8am (e.g. 12am to 7am) depending on energy retailer
A54: Battery energy intensity - Full Loaded | B54: kWh/km | C54: 1.37
A55: Battery energy intensity - Full Loaded - Second Year | B55: kWh/km | C55: =C54*(1+C51) -> 1.37685
A56: Battery energy intensity - Full Loaded - Third Year | B56: kWh/km | C56: =C55*(1+C51) -> 1.3837342
A57: Battery energy intensity - Full Loaded - Fourth Year | B57: kWh/km | C57: =C56*(1+C51) -> 1.3906529
A58: Battery energy intensity - Full Loaded - Fifth Year | B58: kWh/km | C58: =C57*(1+C51) -> 1.3976062
A59: Battery energy intensity - Unladen | B59: KWh/km | C59: =C54*(1-C52) -> 1.0275
A60: Battery energy intensity - Unladen - Second Year | B60: KWh/km | C60: =C55*(1-C52) -> 1.0326375
A61: Battery energy intensity - Unladen - Third Year | B61: KWh/km | C61: =C56*(1-C52) -> 1.0378007
A62: Battery energy intensity - Unladen - Fourth Year | B62: KWh/km | C62: =C57*(1-C52) -> 1.0429897
A63: Battery energy intensity - Unladen - Fifth Year | B63: KWh/km | C63: =C58*(1-C52) -> 1.0482046
A64: Daily truck energy use | B64: kWh | C64: =(C$46*C$49*C54+C$47*C$49*C59) -> 434.48571
A65: Daily truck energy use -Second Year | B65: kWh | C65: =(C$46*C$49*C55+C$47*C$49*C60) -> 436.65814
A66: Daily truck energy use -Third Year | B66: kWh | C66: =(C$46*C$49*C56+C$47*C$49*C61) -> 438.84143
A67: Daily truck energy use - Fourth Year | B67: kWh | C67: =(C$46*C$49*C57+C$47*C$49*C62) -> 441.03564
A68: Daily truck energy use -Fifth Year | B68: kWh | C68: =(C$46*C$49*C58+C$47*C$49*C63) -> 443.24082
A69: Electricity Emissions | B69: kg CO2e/kWh | C69: 0.196
A71: Station specifications
A72: Battery CAPEX | B72: £ | C72: =C28*C29*(C76+C80*C8) -> 4502293.2
A73: Station CAPEX | B73: £ | C73: 2000000 | D73: CATL provided quote | E73: Total station CAPEX includes swapping station hardware and NRE to make fit for UK market | F73: Total station CAPEX includes swapping station hardware and NRE to make fit for UK market
A74: Site CAPEX | B74: £ | C74: 1000000 | D74: Aegis management assumption | E74: Includes civils, construction & comissioning cost
A76: Batteries in station | B76: # | C76: 24 | D76: (NewQQ, 2024)
A77: Station lifetime | B77: years | C77: 15 | D77: CATL management assumption
A78: Max station service capacity | B78: trucks/day | C78: 171 | D78: CATL provided specification | E78: For standard station, limited by battery charging time, swap time, and holding capacity
A79: Expected station utilisation | B79: - | C79: 0.3 | D79: Aegis management assumption | E79: As a percentage of max eHGVs served
A80: Expected station service demand | B80: trucks/day | C80: =C78*C79 -> 51.3 | D80: Aegis model calculation | E80: Octopus claim for 'giant station 1' they need 100 vehicles to breakeven, which checks out with our model (102)
A81: Station Costs and Revenue sources
A82: Station annual staff costs | B82: £/year | C82: 216000
A83: Station annual cost on all other services | B83: £/year | C83: 48705
A84: Annual Allocated Station Operating Cost per truck | B84: £ | C84: =(C82+C83)/C80 -> 5159.9415
A85: Annual Allocated infrastructure depreciation per truck | B85: £ | C85: =((C73 + C74) / C77) / C80 -> 3898.6355 | D85: =((C73 + C74) *C108)/C80 -> 7688.525
A86: Annual Allocated battery depreciation per truck | B86: £ | C86: =(((C76*C28*C29)+(C80*C8*C28*C29))*(1-C30)*(C48*C49*C80*C8/(C31*(C76+C80*C8)))/C80) -> 9069.4669
A87: Basic annual rent to cover BaaS costs | B87: £ | C87: =C86+C85+C84 -> 18128.044 | D87: =C87*5+C90*5 -> 147583.22
A88: Basic monthly rent to cover costs | B88: £ | C88: =C87/12 -> 1510.6703
A89: Expected annual return on battery renting | B89: - | C89: 0.15
A90: Annual extra rent serves as profit | B90: £ | C90: =C29*C8*C28*C89 -> 11388.6
A91: Extra monthly rent | B91: £ | C91: =C90/12 -> 949.05
A92: Swapping fee (flat rate) | B92: £ | C92: 3 | D92: Aegis management assumption
A93: Annual Swapping fee | B93: £ | C93: =C92*C50*C48 -> 876
A94: Peak retail energy price-BaaS provider pays | B94: £/kWh | C94: 0.2 | D94: Aegis management assumption | E94: Peak daytime price (Octopus claim top-end) | F94: Public charging costs can vary significantly. As of October 2025, slow and fast chargers average around 53p per kWh, while rapid and ultra-rapid chargers can cost about 76p per kWh. Switch to an EV-friendly off-peak tariff, and the savings are dramatic. Some suppliers, like Octopus and OVO, offer overnight rates from just 7p per kWh (LOVEELECTRIC, 2025)
A95: Off-peak retail energy price-BaaS provider pays | B95: £/kWh | C95: 0.1 | D95: Aegis management assumption | E95: Off-peak overnight price (Octopus can do £0 for consumer)
A96: Target electricity margin | B96: - | C96: 1 | D96: Aegis management assumption | E96: What Aegis wants to make on energy service offering
A97: Peak retail energy price-Fleet manager pays | B97: £/kWh | C97: =C94*(1+C96) -> 0.4
A98: Off-peak retail energy price-Fleet manager pays | B98: £/kWh | C98: =C95*(1+C96) -> 0.2
A100: Discounted Factors
A101: Discounted Rate | B101: - | C101: 0.1
A102: Discounted Factor:
A103: Year 1 | B103: - | C103: =1/(1+C101)^1 -> 0.90909091
A104: Year 2 | B104: - | C104: =1/(1+C101)^2 -> 0.82644628
A105: Year 3 | B105: - | C105: =1/(1+C101)^3 -> 0.7513148
A106: Year 4 | B106: - | C106: =1/(1+C101)^4 -> 0.68301346
A107: Year 5 | B107: - | C107: =1/(1+C101)^5 -> 0.62092132
...

Sheet BET-C(5)LCE
A1: BET-C (Depot Slow & Hub Fast)
A3: Assumptions
A4: 1. A truck discussed in this model is a heavy-duty vehicle consists of a 6×2 tractor unit. 2. BET fuel economy is assumed to increase every year at 1.4%. 3. All future cash flows and amortised costs are assumed to pay at the end of each year when accounting for discounted values.
A5: Parameter | B5: Units | C5: Public Available Value | D5: Source | E5: Notes from Aegis | F5: Notes for public available data
A6: Truck specifications
A7: Electric Glider Price | B7: £ | C7: 130000 | D7: from Iveco
A8: Total battery capacity | B8: kWh | C8: 513 | D8: (Daimler, 2026)
A9: Initial battery price | B9: £/kWh | C9: 148 | D9: CATL provided quote | E9: Used in Aegis model - adjusted for exchange rate of CNY/GBP of 9.65 (CNY 1,430) | F9: Used in Aegis model - adjusted for exchange rate of CNY/GBP of 9.65 (CNY 1,430)
A10: Electric truck CAPEX | B10: £ | C10: =C7+C8*C9 -> 205924 | E10: Based on Rogers's (MAN Trucks) quotes across a range of vehicle sizes
A11: Glider Fixed depreciation rate | B11: - | C11: 0.075
A12: Variable glider dipreciation per km | B12: £ | C12: 0.095
A13: Glider residual value (EOL) ratio | B13: - | C13: 0.2 | D13: Aegis management assumption | E13: to align with Octopus numbers | F13: to align with Octopus numbers
A14: Glider lifetime | B14: years | C14: 15 | D14: Aegis management assumption | E14: pegged to battery life, which is extended due to less battery cycling overall
A15: Cost of Capital | B15: - | C15: 0.125
A16: Upfront payment percentage | B16: - | C16: 0.3
A17: Loan Term | B17: years | C17: 5
A18: Loan Amount | B18: £ | C18: =C10*(1-C16) -> 144146.8
A19: Upfront payment | B19: £ | C19: =C10*C16 -> 61777.2
A20: Interest payment per year | B20: £ | C20: =C10*(1-C16)*C15 -> 18018.35
A21: Annual payment | B21: £ | C21: =-PMT(C15,5,C18) -> 40484.211
A22: Truck Total Costs NPV | B22: £ | C22: =C21*SUM(C97:C101)+C19 -> 215244.21
A23: Glider weight | B23: kg | C23: 9986
A24: Glider Production Emission Factor | B24: kg CO2e/kg | C24: 7
A25: Glider Recycle Emission Saving | B25: - | C25: 0.17
A27: Battery specifications
A28: Battery residual percentage | B28: - | C28: 0.1 | D28: Provided by Brunp | F28: Collected from Brunp consultation
A29: Battery Lifetime cycle | B29: - | C29: 2200
A30: Battery lifetime | B30: years | C30: =C29/C45 -> 7.5342466
A31: Battery Production Emission Factor | B31: kg CO2e/kWh | C31: 57
A32: Battery Recycle Emission Saving | B32: - | C32: 0.05
A33: Battery Sets Needed | B33: - | C33: 2
A35: Truck Fixed Annual Operation Costs
A36: Annual service cost | B36: £/year | C36: 4200 | D36: Same as BET-C
A37: Diesel truck consistant Insurance | B37: £ | C37: 10000
A38: Insurance percentage on top of diesel truck | B38: - | C38: 0.2
A39: BET insurance | B39: £ | C39: =C37*(1+C38) -> 12000
A40: Driver costs per truck | B40: £/year | C40: =C175*C46 -> 41469.84
A42: Truck Operations Details
A43: Daily distance driven with cargo per shift | B43: km | C43: 240 | E43: derived in model, but used as starting basis here
A44: Daily unladen distance driven per shift | B44: km | C44: =C43/7*3 -> 102.85714 | D44: (DfT, 2024) | F44: The ratio of full-loaded and unladen driven distance is 7:3 in the UK
A45: Operational days per year | B45: days | C45: 292 | D45: Aegis management assumption | E45: 80% utilisation rate of trucks on days in the year basis
A46: Shift per day | B46: - | C46: 1
A47: Charges per day | B47: Charges/day | C47: =MAX(1,(ROUNDUP(((C43+C44)*C46)/(C8/C51),0))) -> 1
A48: Truck fuel economy increase rate | B48: - | C48: 0.014
A49: Energy save compared to when full-loaded | B49: - | C49: 0.25 | D49: ICCT, 2022 | F49: Unladen trucks are assumed to have this % of energy save compared to when full-loaded.
A50: Depot slow charging percentage | B50: - | C50: 0.8 | D50: Aegis management assumption | E50: based on classic 80:20 split depot:public
A51: Truck fuel economy in the first year -Full Loaded | B51: kWh/km | C51: 1.37 | D51: Literature average | E51: assumed same battery technology (CATL) as used in battery swapping truck
A52: Truck fuel economy in the second year -Full Loaded | B52: kWh/km | C52: =C51*(1+C48) -> 1.38918 | F52: assumed energy efficiency decreases over time
A53: Truck fuel economy in the third year -Full Loaded | B53: kWh/km | C53: =C52*(1+C48) -> 1.4086285
A54: Truck fuel economy in the fourth year -Full Loaded | B54: kWh/km | C54: =C53*(1+C48) -> 1.4283493
A55: Truck fuel economy in the fifth year -Full Loaded | B55: kWh/km | C55: =C54*(1+C48) -> 1.4483462
A56: Truck fuel economy in the first year -Unladen | B56: kWh/km | C56: =C51*(1-C49) -> 1.0275
A57: Truck fuel economy in the second year -Unladen | B57: kWh/km | C57: =C52*(1-C49) -> 1.041885
A58: Truck fuel economy in the third year -Unladen | B58: kWh/km | C58: =C53*(1-C49) -> 1.0564714
A59: Truck fuel economy in the fourth year -Unladen | B59: kWh/km | C59: =C54*(1-C49) -> 1.071262
A60: Truck fuel economy in the fifth year -Unladen | B60: kWh/km | C60: =C55*(1-C49) -> 1.0862597
A61: Daily truck energy use in the first year | B61: kWh | C61: =(C$43*C$46*C51+C$44*C$46*C56) -> 434.48571
A62: Daily truck energy use in the second year | B62: kWh | C62: =(C$43*C$46*C52+C$44*C$46*C57) -> 440.56851
A63: Daily truck energy use in the third year | B63: kWh | C63: =(C$43*C$46*C53+C$44*C$46*C58) -> 446.73647
A64: Daily truck energy use in the fourth year | B64: kWh | C64: =(C$43*C$46*C54+C$44*C$46*C59) -> 452.99078
A65: Daily truck energy use in the fifth year | B65: kWh | C65: =(C$43*C$46*C55+C$44*C$46*C60) -> 459.33266
A66: Electricity Emissions | B66: kg CO2e/kWh | C66: 0.196
A68: Depot charging specifications
A69: Charger CAPEX | B69: £/kWh | C69: 0.12 | D69: Aegis management assumption | E69: Done per kWh rather than per charger, due to range of depot requirements
A70: Charger lifetime | B70: years | C70: 8 | D70: Aegis management assumption | E70: Planned obselesence in line with Truck upgrades
A71: Site CAPEX | B71: £/kWh | C71: 0.08 | D71: Aegis management assumption | E71: Includes civils, construction & comissioning cost
A72: Site lifetime | B72: years | C72: 24 | D72: Aegis management assumption | E72: Assume long-term planning for on-depot works
A74: Charging operations
A75: On-depot retail energy price | B75: £/kWh | C75: 0.22 | D75: Aegis management assumption | E75: Flat rate price Aegis get from Octopus currently
A76: Public hub electricity price | B76: £/kWh | C76: 0.39 | D76: Aegis management assumption | E76: What Aegis will currently charge for the best deal
A77: Expected fleet size | B77: trucks | C77: 51 | D77: Aegis management assumption | E77: Use same number as expected utilisation rate from swapping model
A78: Annual energy requirement in the first year | B78: kWh/year | C78: =C61*C47*C77*C45 -> 6470361.3
A79: Annual energy requirement in the second year | B79: kWh/year | C79: =C62*C47*C77*C45 -> 6560946.3
A80: Annual energy requirement in the third year | B80: kWh/year | C80: =C63*C47*C77*C45 -> 6652799.6
A81: Annual energy requirement in the fourth year | B81: kWh/year | C81: =C64*C47*C77*C45 -> 6745938.8
A82: Annual energy requirement in the fifth year | B82: kWh/year | C82: =C65*C47*C77*C45 -> 6840381.9
A83: Annual on-depot demand in the first year | B83: kWh/year | C83: =C50*C78 -> 5176289 | E83: Assume on-depot infrastructure if fully-specificed to handle 100% capacity simultaneously
A84: Annual on-depot demand in the second year | B84: kWh/year | C84: =C50*C79 -> 5248757.1
A85: Annual on-depot demand in the third year | B85: kWh/year | C85: =C50*C80 -> 5322239.7
A86: Annual on-depot demand in the fourth year | B86: kWh/year | C86: =C50*C81 -> 5396751
A87: Annual on-depot demand in the fifth year | B87: kWh/year | C87: =C50*C82 -> 5472305.5
A88: Annual public hub demand in the first year | B88: kWh/year | C88: =C78*(1-C50) -> 1294072.3 | E88: Assume public hub infrastructure if fully-specificed to handle 100% capacity simultaneously
A89: Annual public hub demand in the second year | B89: kWh/year | C89: =C79*(1-C50) -> 1312189.3
A90: Annual public hub demand in the third year | B90: kWh/year | C90: =C80*(1-C50) -> 1330559.9
A91: Annual public hub demand in the fourth year | B91: kWh/year | C91: =C81*(1-C50) -> 1349187.8
A92: Annual public hub demand in the fifth year | B92: kWh/year | C92: =C82*(1-C50) -> 1368076.4
A94: Discounted Factors
A95: Discounted Rate | B95: - | C95: 0.1 | D95: Assumed
A96: Discounted Factor:
A97: Year 1 | B97: - | C97: =1/(1+C95)^1 -> 0.90909091
A98: Year 2 | B98: - | C98: =1/(1+C95)^2 -> 0.82644628
A99: Year 3 | B99: - | C99: =1/(1+C95)^3 -> 0.7513148
A100: Year 4 | B100: - | C100: =1/(1+C95)^4 -> 0.68301346
A101: Year 5 | B101: - | C101: =1/(1+C95)^5 -> 0.62092132
A102: Subsidy
A103: Subsidy | B103: £ | C103: 0 | D103: (GOV.UK, 2023) | F103: from 25000 and up to 120,000 pounds by 2026. Not considered hear but in the subsidy scenarios
A105: Calculations
A106: 10-year Life Cycle Emissions per Truck
A107: Glider Production Emissions | B107: kg CO2e | C107: =C24*C23 -> 69902
A108: Battery Production Emissions | B108: kg CO2e | C108: =C8*C31*C33 -> 58482
...

Sheet Diesel(5)LCE
A1: Diesel Trucks (Depot&Hub)
A3: Assumptions
A4: 1. A truck discussed in this model is a heavy duty vehicle consists of a 6×2 tractor unit. 2. The fuel economy is assumed to increase every year at 1.1%. 3. All future cash flows and amortised costs are assumed to pay at the end of each year when accounting for discounted values.
A5: Parameter | B5: Units | C5: Public Available Value | D5: Source | E5: Notes from Aegis | F5: Notes for public available data
A6: Truck specifications
A8: Diesel truck CAPEX | B8: £ | C8: 144900 | F8: Average price of 5 models
A9: Fixed depreciation rate | B9: - | C9: 0.075
A10: Variable depreciation per km | B10: £ | C10: 0.095
A11: Truck lifetime | B11: years | C11: 15 | D11: Aegis management assumption
A12: Cost of Capital | B12: - | C12: 0.125
A13: Upfront payment percentage | B13: - | C13: 0.3
A14: Loan Term | B14: years | C14: 5
A15: Loan Amount | B15: £ | C15: =C8*(1-C13) -> 101430
A16: Upfront payment | B16: £ | C16: =C8*C13 -> 43470
A17: Interest payment per year | B17: £ | C17: =C8*(1-C13)*C12 -> 12678.75
A18: Annual payment | B18: £ | C18: =-PMT(C12,5,C15) -> 28487.025
A19: Truck Total Costs NPV | B19: £ | C19: =C18*SUM(C102:C106)+C16 -> 151458.24
A20: Truck Curb Weight | B20: kg | C20: 11022
A21: Truck Production Emission Factor | B21: kg CO2e/kg | C21: 7
A22: Diesel Truck Recycle Emission Saving | B22: - | C22: 0.17
A23: Truck Life Cycle Considered Lifetime | B23: years | C23: 10
A25: Truck Fixed Annual Operation Costs
A26: Annual service cost | B26: £/year | C26: 4800 | D26: Aegis management assumption | E26: aligned to Octopus model of £400 per month
A27: Consistent Insurance | B27: £ | C27: 10000 | D27: (Nimblefins, 2026) (Switcha, 2025) | F27: As of January 2026, the average cost to insure a single HGV typically ranges from £5,000 to £10,000 per year. Taking the highest number to represent the large truck model.
A28: Driver costs per truck | B28: £ | C28: =C178*C35 -> 41469.84
A31: Truck operations
A32: Daily distance driven - Full Loaded | B32: km | C32: 240 | E32: derived in model, but used as starting basis here
A33: Daily unladen distance driven | B33: km | C33: =C32/7*3 -> 102.85714 | D33: (DfT, 2024)
A34: Operational days per year | B34: days | C34: 292 | D34: Aegis management assumption | E34: 80% utilisation rate of trucks on days in the year basis
A35: Shift per day | B35: - | C35: 1
A36: Refuels per day | B36: Refuel/day | C36: =C35 -> 1 | D36: Aegis management assumption
A37: Truck fuel economy annual increase rate | B37: - | C37: 0.011
A38: Energy save compared to when full-loaded | B38: - | C38: 0.25 | D38: ICCT, 2022 | F38: Unladen trucks are assumed to have this % of energy save compared to when full-loaded.
A39: Depot refuelling percentage | B39: - | C39: 0.8 | D39: Aegis management assumption | E39: based on classic 80:20 split depot:public
A40: Daily diesel use in the first year | B40: l | C40: =C$32*C$35*C50+C$33*C$35*C60 -> 111
A41: Daily diesel use in the second year | B41: l | C41: =C$32*C$35*C51+C$33*C$35*C61 -> 112.221 | E41: assumed energy efficiency decreases over time
A42: Daily diesel use in the third year | B42: l | C42: =C$32*C$35*C52+C$33*C$35*C62 -> 113.45543
A43: Daily diesel use in the fourth year | B43: l | C43: =C$32*C$35*C53+C$33*C$35*C63 -> 114.70344
A44: Daily diesel use in the fifth year | B44: l | C44: =C$32*C$35*C54+C$33*C$35*C64 -> 115.96518
A45: Daily diesel use in the sixth year | B45: l | C45: =C$32*C$35*C55+C$33*C$35*C65 -> 117.2408
A46: Daily diesel use in the seventh year | B46: l | C46: =C$32*C$35*C56+C$33*C$35*C66 -> 118.53044
A47: Daily diesel use in the eighth year | B47: l | C47: =C$32*C$35*C57+C$33*C$35*C67 -> 119.83428
A48: Daily diesel use in the ninth year | B48: l | C48: =C$32*C$35*C58+C$33*C$35*C68 -> 121.15246
A49: Daily diesel use in the tenth year | B49: l | C49: =C$32*C$35*C59+C$33*C$35*C69 -> 122.48513
A50: Truck fuel economy in the first year -Full Loaded | B50: l/km | C50: 0.35 | D50: Aegis model calculation
A51: Truck fuel economy in the second year -Full Loaded | B51: l/km | C51: =C50*(1+C$37) -> 0.35385
A52: Truck fuel economy in the third year -Full Loaded | B52: l/km | C52: =C51*(1+C$37) -> 0.35774235
A53: Truck fuel economy in the fourth year -Full Loaded | B53: l/km | C53: =C52*(1+C$37) -> 0.36167752
A54: Truck fuel economy in the fifth year -Full Loaded | B54: l/km | C54: =C53*(1+C$37) -> 0.36565597
A55: Truck fuel economy in the sixth year -Full Loaded | B55: l/km | C55: =C54*(1+C$37) -> 0.36967818
A56: Truck fuel economy in the seventh year -Full Loaded | B56: l/km | C56: =C55*(1+C$37) -> 0.37374464
A57: Truck fuel economy in the eighth year -Full Loaded | B57: l/km | C57: =C56*(1+C$37) -> 0.37785584
A58: Truck fuel economy in the ninth year -Full Loaded | B58: l/km | C58: =C57*(1+C$37) -> 0.38201225
A59: Truck fuel economy in the tenth year -Full Loaded | B59: l/km | C59: =C58*(1+C$37) -> 0.38621438
A60: Truck fuel economy in the first year -Unladen | B60: l/km | C60: =C50*(1-C$38) -> 0.2625
A61: Truck fuel economy in the second year -Unladen | B61: l/km | C61: =C51*(1-C$38) -> 0.2653875
A62: Truck fuel economy in the third year -Unladen | B62: l/km | C62: =C52*(1-C$38) -> 0.26830676
A63: Truck fuel economy in the fourth year -Unladen | B63: l/km | C63: =C53*(1-C$38) -> 0.27125814
A64: Truck fuel economy in the fifth year -Unladen | B64: l/km | C64: =C54*(1-C$38) -> 0.27424198
A65: Truck fuel economy in the sixth year -Unladen | B65: l/km | C65: =C55*(1-C$38) -> 0.27725864
A66: Truck fuel economy in the seventh year -Unladen | B66: l/km | C66: =C56*(1-C$38) -> 0.28030848
A67: Truck fuel economy in the eighth year -Unladen | B67: l/km | C67: =C57*(1-C$38) -> 0.28339188
A68: Truck fuel economy in the ninth year -Unladen | B68: l/km | C68: =C58*(1-C$38) -> 0.28650919
A69: Truck fuel economy in the tenth year -Unladen | B69: l/km | C69: =C59*(1-C$38) -> 0.28966079
A70: LEZ operation percentage | B70: - | C70: 0.1 | D70: Assumption
A71: LEZ operation Charge | B71: £ | C71: 50 | D71: (RAM Tracking, 2025)
A72: Diesel Emission Factor | B72: kg CO2e/L | C72: 3.17257
A74: On-depot specifications
A76: Bunker CAPEX | B76: £/l | C76: 0.24 | E76: Includes civils, construction & comissioning cost
A77: Bunker lifetime | B77: years | C77: 24 | E77: Assume long-term planning for on-depot works
A79: Refuelling operations
A80: wholesale diesel price | B80: £/l | C80: 1.05 | D80: Aegis management assumption | E80: Flat rate price Aegis get from Octopus currently
A81: Public hub diesel price | B81: £/l | C81: 1.48 | D81: (DfT, 2025b) | E81: What the market rate of diesel currently is (excl. VAT) | F81: Average diesel price was 148 pence per litre in 2024
A82: Expected fleet size | B82: trucks | C82: 51 | D82: Aegis management assumption | E82: Use same number as expected utilisation rate from swapping model
A83: Expected diesel requirement in the first year | B83: l/day | C83: =C40*C36*C82*C34 -> 1653012 | D83: Aegis model calculation
A84: Expected diesel requirement in the second year | B84: l/day | C84: =C41*C36*C82*C34 -> 1671195.1
A85: Expected diesel requirement in the third year | B85: l/day | C85: =C42*C36*C82*C34 -> 1689578.3
A86: Expected diesel requirement in the fourth year | B86: l/day | C86: =C43*C36*C82*C34 -> 1708163.6
A87: Expected diesel requirement in the fifth year | B87: l/day | C87: =C44*C36*C82*C34 -> 1726953.4
A88: Annual on-depot demand in the first year | B88: l/day | C88: =C39*C83 -> 1322409.6 | D88: Aegis model calculation | E88: Assume on-depot infrastructure if fully-specificed to handle 100% capacity simultaneously
A89: Annual on-depot demand in the secodn year | B89: l/day | C89: =C39*C84 -> 1336956.1
A90: Annual on-depot demand in the third year | B90: l/day | C90: =C39*C85 -> 1351662.6
A91: Annual on-depot demand in the fourth year | B91: l/day | C91: =C39*C86 -> 1366530.9
A92: Annual on-depot demand in the fifth year | B92: l/day | C92: =C39*C87 -> 1381562.8
A93: Annual public hub demand in the first year | B93: l/day | C93: =C83*(1-C39) -> 330602.4 | D93: Aegis model calculation | E93: Assume public hub infrastructure if fully-specificed to handle 100% capacity simultaneously
A94: Annual public hub demand in the second year | B94: l/day | C94: =C84*(1-C39) -> 334239.03
A95: Annual public hub demand in the third year | B95: l/day | C95: =C85*(1-C39) -> 337915.66
A96: Annual public hub demand in the fourth year | B96: l/day | C96: =C86*(1-C39) -> 341632.73
A97: Annual public hub demand in the fifth year | B97: l/day | C97: =C87*(1-C39) -> 345390.69
A99: Discounted Factors
A100: Discounted Rate | B100: - | C100: 0.1
A101: Discounted Factor:
A102: Year 1 | B102: - | C102: =1/(1+C100)^1 -> 0.90909091
A103: Year 2 | B103: - | C103: =1/(1+C100)^2 -> 0.82644628
A104: Year 3 | B104: - | C104: =1/(1+C100)^3 -> 0.7513148
A105: Year 4 | B105: - | C105: =1/(1+C100)^4 -> 0.68301346
A106: Year 5 | B106: - | C106: =1/(1+C100)^5 -> 0.62092132
A108: Calculations
A109: 10-year Life Cycle Emissions per Truck
A110: Truck Production Emissions | B110: kg CO2e | C110: =C20*C21 -> 77154
...

Sheet Future Dynamic Input
A1: Input future changes
A2: Variable | B2: annual change by 2030 | C2: Reference | D2: annual change by 2040 | E2: Reference
A3: Diesel truck acquisition cost | B3: 0.01 | C3: ICCT, 2021 | D3: 0.005 | E3: Assumed
A4: Electric glider acquisition cost | B4: -0.06 | C4: ICCT, 2024, ICCT, 2021 + ASSUMED | D4: -0.03 | E4: Assumed
A5: Initial battery price | B5: -0.08 | C5: ICCT, 2024, ICCT, 2021 | D5: -0.04 | E5: Assumed
A6: Fuel economy in the purchase year -Full Loaded - Diesel | B6: -0.026 | C6: ICCT, 2021 | D6: -0.013 | E6: Assumed
A7: Fuel economy in the purchase year -Full Loaded - BET-C&BET-S | B7: -0.031 | C7: ICCT, 2021 | D7: -0.015 | E7: Assumed
A8: Battery Lifetime cycle | B8: 200 | C8: ICCT, 2024 | D8: 200 | E8: ICCT, 2024
